python_schema/__init__.py
python_schema/exception.py
python_schema/misc.py
python_schema/field/__init__.py
python_schema/field/base_field.py
python_schema/field/collection_field.py
python_schema/field/int_field.py
python_schema/field/schema_field.py
python_schema/field/str_field.py
python_schema-0.4.1.dist-info/LICENSE
python_schema-0.4.1.dist-info/METADATA
python_schema-0.4.1.dist-info/WHEEL
python_schema-0.4.1.dist-info/top_level.txt
python_schema-0.4.1.dist-info/RECORD
