Metadata-Version: 2.1
Name: python-schema
Version: 0.4.1
Summary: Simple but not simplistic schema for data-validation
Home-page: https://github.com/Drachenfels/python-schema
Author: Drachenfels <drachenfels@protonmail.com>
Author-email: drachenfels@protonmail.com
License: MIT
Keywords: schema
Platform: UNKNOWN
Classifier: Development Status :: 1 - Planning
Classifier: Intended Audience :: Developers
Classifier: Programming Language :: Python :: 3 :: Only
Classifier: Programming Language :: Python :: 3.7
Classifier: Topic :: Software Development
Requires-Python: >=3.7
